pytest_copier-0.4.1.dist-info/METADATA
pytest_copier-0.4.1.dist-info/WHEEL
pytest_copier-0.4.1.dist-info/entry_points.txt
pytest_copier-0.4.1.dist-info/licenses/LICENSE
pytest_copier/.gitignore
pytest_copier/VERSION
pytest_copier/__init__.py
pytest_copier/errors.py
pytest_copier/plugin.py
pytest_copier/py.typed
pytest_copier-0.4.1.dist-info/RECORD
