Metadata-Version: 2.1
Name: pytest-copier
Version: 0.4.1
Summary: A pytest plugin to help testing Copier templates
Author-Email: Axel Haustant <noirbizarre@gmail.com>
License: MIT
Classifier: Development Status :: 4 - Beta
Classifier: Intended Audience :: Developers
Classifier: Programming Language :: Python
Classifier: Programming Language :: Python :: 3
Classifier: Programming Language :: Python :: 3 :: Only
Classifier: Programming Language :: Python :: 3.8
Classifier: Programming Language :: Python :: 3.9
Classifier: Programming Language :: Python :: 3.10
Classifier: Programming Language :: Python :: 3.11
Classifier: Programming Language :: Python :: 3.12
Classifier: Typing :: Typed
Project-URL: Homepage, https://github.com/noirbizarre/pytest-copier
Project-URL: Documentation, https://github.com/noirbizarre/pytest-copier#readme
Project-URL: Repository, https://github.com/noirbizarre/pytest-copier
Project-URL: Issues, https://github.com/noirbizarre/pytest-copier/issues
Requires-Python: >=3.8
Requires-Dist: pytest>=7.3.2
Requires-Dist: copier>=9.0.0
Requires-Dist: pytest-dir-equal>=0.2
Requires-Dist: pytest-gitconfig>=0.4
